{
  "spreadsheetId": "1ZUDnN-gkgfC0BMuwdZp2hP6yQhhMp3bCt_VA-NqTl9g",
  "properties": {
    "title": "訪問看護_利用者管理_保険管理",
    "locale": "ja_JP",
    "autoRecalc": "ON_CHANGE",
    "timeZone": "Asia/Tokyo",
    "defaultFormat": {
      "backgroundColor": {
        "red": 1,
        "green": 1,
        "blue": 1
      },
      "padding": {
        "top": 2,
        "right": 3,
        "bottom": 2,
        "left": 3
      },
      "verticalAlignment": "BOTTOM",
      "wrapStrategy": "OVERFLOW_CELL",
      "textFormat": {
        "foregroundColor": {},
        "fontFamily": "arial,sans,sans-serif",
        "fontSize": 10,
        "bold": false,
        "italic": false,
        "strikethrough": false,
        "underline": false,
        "foregroundColorStyle": {
          "rgbColor": {}
        }
      },
      "backgroundColorStyle": {
        "rgbColor": {
          "red": 1,
          "green": 1,
          "blue": 1
        }
      }
    },
    "spreadsheetTheme": {
      "primaryFontFamily": "Arial",
      "themeColors": [
        {
          "colorType": "TEXT",
          "color": {
            "rgbColor": {}
          }
        },
        {
          "colorType": "BACKGROUND",
          "color": {
            "rgbColor": {
              "red": 1,
              "green": 1,
              "blue": 1
            }
          }
        },
        {
          "colorType": "ACCENT1",
          "color": {
            "rgbColor": {
              "red": 0.25882354,
              "green": 0.52156866,
              "blue": 0.95686275
            }
          }
        },
        {
          "colorType": "ACCENT2",
          "color": {
            "rgbColor": {
              "red": 0.91764706,
              "green": 0.2627451,
              "blue": 0.20784314
            }
          }
        },
        {
          "colorType": "ACCENT3",
          "color": {
            "rgbColor": {
              "red": 0.9843137,
              "green": 0.7372549,
              "blue": 0.015686275
            }
          }
        },
        {
          "colorType": "ACCENT4",
          "color": {
            "rgbColor": {
              "red": 0.20392157,
              "green": 0.65882355,
              "blue": 0.3254902
            }
          }
        },
        {
          "colorType": "ACCENT5",
          "color": {
            "rgbColor": {
              "red": 1,
              "green": 0.42745098,
              "blue": 0.003921569
            }
          }
        },
        {
          "colorType": "ACCENT6",
          "color": {
            "rgbColor": {
              "red": 0.27450982,
              "green": 0.7411765,
              "blue": 0.7764706
            }
          }
        },
        {
          "colorType": "LINK",
          "color": {
            "rgbColor": {
              "red": 0.06666667,
              "green": 0.33333334,
              "blue": 0.8
            }
          }
        }
      ]
    }
  },
  "sheets": [
    {
      "properties": {
        "sheetId": 0,
        "title": "Client_Medical_Insurances",
        "index": 0,
        "sheetType": "GRID",
        "gridProperties": {
          "rowCount": 1000,
          "columnCount": 28,
          "frozenRowCount": 1
        }
      },
      "bandedRanges": [
        {
          "bandedRangeId": 90474226,
          "range": {
            "startRowIndex": 0,
            "endRowIndex": 1000,
            "startColumnIndex": 0,
            "endColumnIndex": 28
          },
          "rowProperties": {
            "headerColor": {
              "red": 0.20784314,
              "green": 0.40784314,
              "blue": 0.32941177
            },
            "firstBandColor": {
              "red": 1,
              "green": 1,
              "blue": 1
            },
            "secondBandColor": {
              "red": 0.9647059,
              "green": 0.972549,
              "blue": 0.9764706
            },
            "headerColorStyle": {
              "rgbColor": {
                "red": 0.20784314,
                "green": 0.40784314,
                "blue": 0.32941177
              }
            },
            "firstBandColorStyle": {
              "rgbColor": {
                "red": 1,
                "green": 1,
                "blue": 1
              }
            },
            "secondBandColorStyle": {
              "rgbColor": {
                "red": 0.9647059,
                "green": 0.972549,
                "blue": 0.9764706
              }
            }
          },
          "bandedRangeReference": "90474226"
        }
      ],
      "tables": [
        {
          "tableId": "90474226",
          "name": "表_2",
          "range": {
            "startRowIndex": 0,
            "endRowIndex": 1000,
            "startColumnIndex": 0,
            "endColumnIndex": 28
          },
          "rowsProperties": {
            "headerColorStyle": {
              "rgbColor": {
                "red": 0.20784314,
                "green": 0.40784314,
                "blue": 0.32941177
              }
            },
            "firstBandColorStyle": {
              "rgbColor": {
                "red": 1,
                "green": 1,
                "blue": 1
              }
            },
            "secondBandColorStyle": {
              "rgbColor": {
                "red": 0.9647059,
                "green": 0.972549,
                "blue": 0.9764706
              }
            }
          },
          "columnProperties": [
            {
              "columnName": "medical_insurance_id"
            },
            {
              "columnIndex": 1,
              "columnName": "status"
            },
            {
              "columnIndex": 2,
              "columnName": "client_id"
            },
            {
              "columnIndex": 3,
              "columnName": "is_currently_active"
            },
            {
              "columnIndex": 4,
              "columnName": "effective_start_date"
            },
            {
              "columnIndex": 5,
              "columnName": "effective_end_date"
            },
            {
              "columnIndex": 6,
              "columnName": "insurer_number"
            },
            {
              "columnIndex": 7,
              "columnName": "policy_symbol"
            },
            {
              "columnIndex": 8,
              "columnName": "policy_number"
            },
            {
              "columnIndex": 9,
              "columnName": "branch_number"
            },
            {
              "columnIndex": 10,
              "columnName": "relationship_to_insured"
            },
            {
              "columnIndex": 11,
              "columnName": "insurance_category"
            },
            {
              "columnIndex": 12,
              "columnName": "is_work_related_reason"
            },
            {
              "columnIndex": 13,
              "columnName": "benefit_rate"
            },
            {
              "columnIndex": 14,
              "columnName": "income_category"
            },
            {
              "columnIndex": 15,
              "columnName": "copayment_category"
            },
            {
              "columnIndex": 16,
              "columnName": "certificate_number"
            },
            {
              "columnIndex": 17,
              "columnName": "fixed_copayment_amount"
            },
            {
              "columnIndex": 18,
              "columnName": "reduction_category"
            },
            {
              "columnIndex": 19,
              "columnName": "reduction_rate_percent"
            },
            {
              "columnIndex": 20,
              "columnName": "reduction_amount"
            },
            {
              "columnIndex": 21,
              "columnName": "reduction_cert_expiration_date"
            },
            {
              "columnIndex": 22,
              "columnName": "source_document_id"
            },
            {
              "columnIndex": 23,
              "columnName": "remarks"
            },
            {
              "columnIndex": 24,
              "columnName": "created_at"
            },
            {
              "columnIndex": 25,
              "columnName": "created_by"
            },
            {
              "columnIndex": 26,
              "columnName": "updated_at"
            },
            {
              "columnIndex": 27,
              "columnName": "updated_by"
            }
          ]
        }
      ]
    },
    {
      "properties": {
        "sheetId": 1237572625,
        "title": "Client_LTCI_Insurances",
        "index": 1,
        "sheetType": "GRID",
        "gridProperties": {
          "rowCount": 1000,
          "columnCount": 19,
          "frozenRowCount": 1
        }
      },
      "bandedRanges": [
        {
          "bandedRangeId": 2076283123,
          "range": {
            "sheetId": 1237572625,
            "startRowIndex": 0,
            "endRowIndex": 1000,
            "startColumnIndex": 0,
            "endColumnIndex": 19
          },
          "rowProperties": {
            "headerColor": {
              "red": 0.20784314,
              "green": 0.40784314,
              "blue": 0.32941177
            },
            "firstBandColor": {
              "red": 1,
              "green": 1,
              "blue": 1
            },
            "secondBandColor": {
              "red": 0.9647059,
              "green": 0.972549,
              "blue": 0.9764706
            },
            "headerColorStyle": {
              "rgbColor": {
                "red": 0.20784314,
                "green": 0.40784314,
                "blue": 0.32941177
              }
            },
            "firstBandColorStyle": {
              "rgbColor": {
                "red": 1,
                "green": 1,
                "blue": 1
              }
            },
            "secondBandColorStyle": {
              "rgbColor": {
                "red": 0.9647059,
                "green": 0.972549,
                "blue": 0.9764706
              }
            }
          },
          "bandedRangeReference": "2076283123"
        }
      ],
      "tables": [
        {
          "tableId": "2076283123",
          "name": "表_1",
          "range": {
            "sheetId": 1237572625,
            "startRowIndex": 0,
            "endRowIndex": 1000,
            "startColumnIndex": 0,
            "endColumnIndex": 19
          },
          "rowsProperties": {
            "headerColorStyle": {
              "rgbColor": {
                "red": 0.20784314,
                "green": 0.40784314,
                "blue": 0.32941177
              }
            },
            "firstBandColorStyle": {
              "rgbColor": {
                "red": 1,
                "green": 1,
                "blue": 1
              }
            },
            "secondBandColorStyle": {
              "rgbColor": {
                "red": 0.9647059,
                "green": 0.972549,
                "blue": 0.9764706
              }
            }
          },
          "columnProperties": [
            {
              "columnName": "ltci_insurance_id"
            },
            {
              "columnIndex": 1,
              "columnName": "status"
            },
            {
              "columnIndex": 2,
              "columnName": "client_id"
            },
            {
              "columnIndex": 3,
              "columnName": "is_currently_active"
            },
            {
              "columnIndex": 4,
              "columnName": "insured_person_number"
            },
            {
              "columnIndex": 5,
              "columnName": "insurer_number"
            },
            {
              "columnIndex": 6,
              "columnName": "insurer_name"
            },
            {
              "columnIndex": 7,
              "columnName": "care_level"
            },
            {
              "columnIndex": 8,
              "columnName": "cert_start_date"
            },
            {
              "columnIndex": 9,
              "columnName": "cert_end_date"
            },
            {
              "columnIndex": 10,
              "columnName": "benefit_rate"
            },
            {
              "columnIndex": 11,
              "columnName": "next_renewal_check_date"
            },
            {
              "columnIndex": 12,
              "columnName": "source_document_id"
            },
            {
              "columnIndex": 13,
              "columnName": "insurance_card_image"
            },
            {
              "columnIndex": 14,
              "columnName": "remarks"
            },
            {
              "columnIndex": 15,
              "columnName": "created_at"
            },
            {
              "columnIndex": 16,
              "columnName": "created_by"
            },
            {
              "columnIndex": 17,
              "columnName": "updated_at"
            },
            {
              "columnIndex": 18,
              "columnName": "updated_by"
            }
          ]
        }
      ]
    },
    {
      "properties": {
        "sheetId": 54816728,
        "title": "Client_LTCI_Copayment_Certificates",
        "index": 2,
        "sheetType": "GRID",
        "gridProperties": {
          "rowCount": 1000,
          "columnCount": 26
        }
      }
    },
    {
      "properties": {
        "sheetId": 1945641531,
        "title": "Client_Public_Subsidies",
        "index": 3,
        "sheetType": "GRID",
        "gridProperties": {
          "rowCount": 1000,
          "columnCount": 24,
          "frozenRowCount": 1
        }
      },
      "bandedRanges": [
        {
          "bandedRangeId": 968235225,
          "range": {
            "sheetId": 1945641531,
            "startRowIndex": 0,
            "endRowIndex": 1000,
            "startColumnIndex": 0,
            "endColumnIndex": 24
          },
          "rowProperties": {
            "headerColor": {
              "red": 0.20784314,
              "green": 0.40784314,
              "blue": 0.32941177
            },
            "firstBandColor": {
              "red": 1,
              "green": 1,
              "blue": 1
            },
            "secondBandColor": {
              "red": 0.9647059,
              "green": 0.972549,
              "blue": 0.9764706
            },
            "headerColorStyle": {
              "rgbColor": {
                "red": 0.20784314,
                "green": 0.40784314,
                "blue": 0.32941177
              }
            },
            "firstBandColorStyle": {
              "rgbColor": {
                "red": 1,
                "green": 1,
                "blue": 1
              }
            },
            "secondBandColorStyle": {
              "rgbColor": {
                "red": 0.9647059,
                "green": 0.972549,
                "blue": 0.9764706
              }
            }
          },
          "bandedRangeReference": "968235225"
        }
      ],
      "tables": [
        {
          "tableId": "968235225",
          "name": "表_3",
          "range": {
            "sheetId": 1945641531,
            "startRowIndex": 0,
            "endRowIndex": 1000,
            "startColumnIndex": 0,
            "endColumnIndex": 24
          },
          "rowsProperties": {
            "headerColorStyle": {
              "rgbColor": {
                "red": 0.20784314,
                "green": 0.40784314,
                "blue": 0.32941177
              }
            },
            "firstBandColorStyle": {
              "rgbColor": {
                "red": 1,
                "green": 1,
                "blue": 1
              }
            },
            "secondBandColorStyle": {
              "rgbColor": {
                "red": 0.9647059,
                "green": 0.972549,
                "blue": 0.9764706
              }
            }
          },
          "columnProperties": [
            {
              "columnName": "public_subsidy_id"
            },
            {
              "columnIndex": 1,
              "columnName": "status"
            },
            {
              "columnIndex": 2,
              "columnName": "client_id"
            },
            {
              "columnIndex": 3,
              "columnName": "is_currently_active"
            },
            {
              "columnIndex": 4,
              "columnName": "subsidy_name"
            },
            {
              "columnIndex": 5,
              "columnName": "priority_rank"
            },
            {
              "columnIndex": 6,
              "columnName": "payer_number"
            },
            {
              "columnIndex": 7,
              "columnName": "recipient_number"
            },
            {
              "columnIndex": 8,
              "columnName": "subsidy_category_number"
            },
            {
              "columnIndex": 9,
              "columnName": "copayment_category"
            },
            {
              "columnIndex": 10,
              "columnName": "income_category"
            },
            {
              "columnIndex": 11,
              "columnName": "benefit_rate_percent"
            },
            {
              "columnIndex": 12,
              "columnName": "limit_unit_type"
            },
            {
              "columnIndex": 13,
              "columnName": "monthly_limit_amount"
            },
            {
              "columnIndex": 14,
              "columnName": "per_service_limit_amount"
            },
            {
              "columnIndex": 15,
              "columnName": "monthly_visit_limit"
            },
            {
              "columnIndex": 16,
              "columnName": "effective_start_date"
            },
            {
              "columnIndex": 17,
              "columnName": "effective_end_date"
            },
            {
              "columnIndex": 18,
              "columnName": "source_document_id"
            },
            {
              "columnIndex": 19,
              "columnName": "remarks"
            },
            {
              "columnIndex": 20,
              "columnName": "created_at"
            },
            {
              "columnIndex": 21,
              "columnName": "created_by"
            },
            {
              "columnIndex": 22,
              "columnName": "updated_at"
            },
            {
              "columnIndex": 23,
              "columnName": "updated_by"
            }
          ]
        }
      ]
    },
    {
      "properties": {
        "sheetId": 1502386600,
        "title": "Client_Subsidy_Monthly_Limits",
        "index": 4,
        "sheetType": "GRID",
        "gridProperties": {
          "rowCount": 999,
          "columnCount": 15
        }
      },
      "bandedRanges": [
        {
          "bandedRangeId": 1673270460,
          "range": {
            "sheetId": 1502386600,
            "startRowIndex": 5,
            "endRowIndex": 7,
            "startColumnIndex": 0,
            "endColumnIndex": 1
          },
          "rowProperties": {
            "firstBandColor": {
              "red": 1,
              "green": 1,
              "blue": 1
            },
            "secondBandColor": {
              "red": 0.9647059,
              "green": 0.972549,
              "blue": 0.9764706
            },
            "firstBandColorStyle": {
              "rgbColor": {
                "red": 1,
                "green": 1,
                "blue": 1
              }
            },
            "secondBandColorStyle": {
              "rgbColor": {
                "red": 0.9647059,
                "green": 0.972549,
                "blue": 0.9764706
              }
            }
          }
        },
        {
          "bandedRangeId": 2074979326,
          "range": {
            "sheetId": 1502386600,
            "startRowIndex": 1,
            "endRowIndex": 4,
            "startColumnIndex": 3,
            "endColumnIndex": 10
          },
          "rowProperties": {
            "firstBandColor": {
              "red": 1,
              "green": 1,
              "blue": 1
            },
            "secondBandColor": {
              "red": 0.9647059,
              "green": 0.972549,
              "blue": 0.9764706
            },
            "firstBandColorStyle": {
              "rgbColor": {
                "red": 1,
                "green": 1,
                "blue": 1
              }
            },
            "secondBandColorStyle": {
              "rgbColor": {
                "red": 0.9647059,
                "green": 0.972549,
                "blue": 0.9764706
              }
            }
          }
        },
        {
          "bandedRangeId": 271867590,
          "range": {
            "sheetId": 1502386600,
            "startRowIndex": 1,
            "endRowIndex": 4,
            "startColumnIndex": 2,
            "endColumnIndex": 3
          },
          "rowProperties": {
            "firstBandColor": {
              "red": 1,
              "green": 1,
              "blue": 1
            },
            "secondBandColor": {
              "red": 0.9647059,
              "green": 0.972549,
              "blue": 0.9764706
            },
            "firstBandColorStyle": {
              "rgbColor": {
                "red": 1,
                "green": 1,
                "blue": 1
              }
            },
            "secondBandColorStyle": {
              "rgbColor": {
                "red": 0.9647059,
                "green": 0.972549,
                "blue": 0.9764706
              }
            }
          }
        }
      ]
    },
    {
      "properties": {
        "sheetId": 1544310697,
        "title": "Public_Subsidy_Master",
        "index": 5,
        "sheetType": "GRID",
        "gridProperties": {
          "rowCount": 999,
          "columnCount": 27
        }
      }
    }
  ],
  "spreadsheetUrl": "https://docs.google.com/spreadsheets/d/1ZUDnN-gkgfC0BMuwdZp2hP6yQhhMp3bCt_VA-NqTl9g/edit?ouid=115875753981822839683"
}